answer_finder/__init__.py
answer_finder/core.py
answer_finder-0.0.0.dist-info/METADATA
answer_finder-0.0.0.dist-info/WHEEL
answer_finder-0.0.0.dist-info/top_level.txt
answer_finder-0.0.0.dist-info/RECORD
